c2f.cp37-win_amd64.pyd
c2f.py
c2f-1.0.5.dist-info/METADATA
c2f-1.0.5.dist-info/WHEEL
c2f-1.0.5.dist-info/top_level.txt
c2f-1.0.5.dist-info/RECORD
